{
  "message": {
    "Floating-window-permission-application": "浮窗权限申请\t",
    "Open": "开启",
    "Permission-not-granted": "权限未授予",
    "Pop-ups1": "你正在使用内部版本，为了正常展示内测反馈入口，需要获取浮窗权限\t",
    "Pop-ups2-1": "浮窗权限未授予，将导致内测反馈无法上传，影响问题排查及活动的正常参与。",
    "Pop-ups2-2": "你可前往「手机设置」-「应用管理」-「高级」-「在其他应用上层显示」进行浮窗设置",
    "authority_success": "授权成功",
    "cancel": "取消",
    "complete": "完成",
    "confirm-cancel": "确认取消\t",
    "enter_feedbacker": "点击本通知进入反馈上报界面",
    "failed_message": "本次校验失败，请重试或进行飞书账密登录授权",
    "feedbacker_running": "内测SDK正在运行",
    "fll_image": "原图",
    "guidepage_title": "内部员工校验",
    "guidepage_title_detail": "内测版应用需前往飞书校验您的身份",
    "hide_float_window": "隐藏",
    "hide_float_window_content": "隐藏后将不再显示反馈浮窗，如需恢复请重新安装应用或更新应用",
    "hide_float_window_title": "隐藏浮窗",
    "jump_to_lark_failed": "跳转到Lark失败",
    "key_i_know": "我知道了",
    "key_please_select_priori": "请选择问题优先级",
    "key_priority_description": "P0 致命：产品无法启动，系统频繁崩溃\nP1 严重：关键功能错误，系统偶尔卡顿、停响等\nP2 重要：功能、界面、性能问题，影响使用\nP3 普通：功能、界面、性能问题、但不影响使用\nP4 微小：不明显的错误信息，对产品发布没有影响",
    "key_priori_title": "问题优先级",
    "key_question_description": "问题描述",
    "key_recurrence": "问题复现频率",
    "key_p0_priority": "P0 致命：",
    "key_p1_priority": "P1 严重：",
    "key_p2_priority": "P2 重要：",
    "key_p3_priority": "P3 普通：",
    "key_p4_priority": "P2 微小：",
    "key_authorizing": "授权中...",
    "network_unavailable": "当前网络已断开，请检查网络后重试",
    "not_get_valid_verify_code": "没有获得有效的授权码",
    "oncall_prefix": "无法跳转？请飞书联系",
    "onCall_number": "内测值班号",
    "getProblem": "反馈遇到问题？前往飞书 内测值班号 告诉我们",
    "sdk_feedback_toast": "未检测到飞书，无法跳转值班号",
    "sdk_permission_check": "应用授权遇到问题？前往飞书 内测值班号 进行反馈",
    "sdk_feedback_popup_content": "问题上报失败，请尝试更换网络或重启APP重试。 若连续上报失败，可前往飞书 内测值班号 反馈。",
    "sdk_feedback_popup_button": "确定",
    "sdk_feedback_remind": "反馈遇到问题？前往飞书 内测值班号 告诉我们",
    "p0": "致命",
    "p1": "严重",
    "p2": "一般",
    "p3": "普通",
    "p4": "微小",
    "preview": "预览",
    "recent": "最近项目",
    "request_params_incorrect": "请求参数错误",
    "packUp": "收起",
    "sdk1": "问题反馈",
    "sdk10": "模块分类",
    "sdk11": "备注反馈",
    "sdk12": "提交",
    "sdk13": "不能愉快的使用现有功能？上传相关页面截图能方便我们快速解决问题哦～",
    "sdk14": "获取标签信息失败，请确保连接公司wifi后重新进入该页面",
    "sdk15": "请选择问题类型",
    "sdk16": "请选择复现次数",
    "sdk17": "请选择分类",
    "sdk18": "描述字数小于5个字",
    "sdk19": "上传中...",
    "sdk2": "反馈",
    "sdk20": "上传组件正在加载中，请稍后重试...",
    "sdk21": "提交成功",
    "sdk22": "用户反馈",
    "sdk23": "连续上报失败，\n请飞书搜索 字节内测用户群  将问题反馈给我们",
    "sdk24": "是否保存当前内容",
    "sdk25": "保存",
    "sdk26": "放弃",
    "sdk27": "问题上报中...",
    "sdk28": "录屏失败了，请重新尝试",
    "sdk29": "无法获取到WindowManager",
    "sdk3": "录屏",
    "sdk30": "无法获取到屏幕宽高信息",
    "sdk31": "截屏失败了，重新尝试一下",
    "sdk32": "录屏失败了，请重新尝试",
    "sdk33": "初始化屏幕录制组件失败",
    "sdk34": "悬浮窗权限被拒绝",
    "sdk37": "问题上报失败\t",
    "sdk38": "再次发送\t",
    "sdk39": "字数超出限制\t",
    "sdk4": "截屏",
    "sdk40": "最多只能输入200字，当前还可输入%ld",
    "sdk41": "无访问权限",
    "sdk42": "请在手机的「设置-隐私-照片」选项中，打开照片访问权限",
    "sdk43": "连续上报失败，请点击用户反馈将问题反馈给我们，我们会尽快修复该问题，或保存草稿，等待网络稳定后重试",
    "sdk5": "上报视频",
    "sdk6": "上报截图",
    "sdk7": "反馈",
    "sdk8": "问题类型",
    "sdk9": "复现次数",
    "sdk_suggestion_1": "所属模块",
    "sdk_suggestion_2": "建议详情",
    "sdk_suggestion_3": "你的建议将展示在字节内测小程序想法论坛中，供其他同学包括该业务线PM、RD查看及互动，并有机会被有缘人选中实现哦~",
    "sdk_submit_feedback": "提交反馈",
    "sdk_submit_feedback_succeed": "问题上报成功",
    "sdk_upload_fail": "连续上报失败，请点击用户反馈将问题反馈给我们，我们会尽快修复",
    "sdk_screenshot_feedback": "截图反馈",
    "sdk_record_feedback": "录屏反馈",
    "sdk_feedback_character_number_limited": "反馈内容应不小于5个字",
    "sso_h5": "飞书账密登录授权",
    "sso_retry": "重试",
    "sso_state_code_verify_failed": "状态码校验失败，非当前SDK请求的响应",
    "sso_verify_success": "校验成功",
    "sso_retrying": "加载中...",
    "sso_network_request_failed": "网络奋力加载中，请耐心等待或更换网络重试",
    "sso_network_connect_overtime": "网络连接超时，请检查网络后重试",
    "sso_network_connect_failed": "网络连接失败，请检查网络后重试",
    "sso_application_exception": "应用异常，请重新启动应用",
    "start_sso": "发起授权",
    "toast_cancel_sso_verify": "你已取消飞书校验",
    "user_cancel_verify": "用户取消授权",
    "verify_failed": "校验失败"
  },
  "status": 200
}
